milestonexprotectrestpython/__init__.py
milestonexprotectrestpython/xpranalyticsevent.py
milestonexprotectrestpython/xprappmessages.py
milestonexprotectrestpython/xprauthenticationtype.py
milestonexprotectrestpython/xprcamera.py
milestonexprotectrestpython/xprchildsite.py
milestonexprotectrestpython/xprcollection.py
milestonexprotectrestpython/xprconst.py
milestonexprotectrestpython/xprdevice.py
milestonexprotectrestpython/xprdevicegroup.py
milestonexprotectrestpython/xprenumcomparable.py
milestonexprotectrestpython/xpreventtype.py
milestonexprotectrestpython/xpreventtypegroup.py
milestonexprotectrestpython/xprexception.py
milestonexprotectrestpython/xprfilteroperator.py
milestonexprotectrestpython/xprgenericevent.py
milestonexprotectrestpython/xprgenericeventdatasource.py
milestonexprotectrestpython/xprhardware.py
milestonexprotectrestpython/xprinputevent.py
milestonexprotectrestpython/xprlicensedetail.py
milestonexprotectrestpython/xprlicenseinformation.py
milestonexprotectrestpython/xprlicenseoverview.py
milestonexprotectrestpython/xprlicenseproduct.py
milestonexprotectrestpython/xprlogininfo.py
milestonexprotectrestpython/xprlogintokenexpiredexception.py
milestonexprotectrestpython/xprmetadata.py
milestonexprotectrestpython/xprmicrophone.py
milestonexprotectrestpython/xprmotiondetection.py
milestonexprotectrestpython/xproutput.py
milestonexprotectrestpython/xprrecordingserver.py
milestonexprotectrestpython/xprrestservice.py
milestonexprotectrestpython/xprrestservicebase.py
milestonexprotectrestpython/xprrestserviceexception.py
milestonexprotectrestpython/xprsite.py
milestonexprotectrestpython/xprsiteowner.py
milestonexprotectrestpython/xprspeaker.py
milestonexprotectrestpython/xprstategroup.py
milestonexprotectrestpython/xprstream.py
milestonexprotectrestpython/xpruserdefinedevent.py
milestonexprotectrestpython/xprutils.py
milestonexprotectrestpython/docs/__init__.html
milestonexprotectrestpython/docs/codecopy.js
milestonexprotectrestpython/docs/index.html
milestonexprotectrestPython-1.0.5.dist-info/LICENSE
milestonexprotectrestPython-1.0.5.dist-info/METADATA
milestonexprotectrestPython-1.0.5.dist-info/WHEEL
milestonexprotectrestPython-1.0.5.dist-info/top_level.txt
milestonexprotectrestPython-1.0.5.dist-info/RECORD
