Metadata-Version: 2.1
Name: milestonexprotectrestPython
Version: 1.0.5
Summary: Milestone XProtect REST Services Python3 Library
Author: Todd Lucas
Author-email: <thlucas@yahoo.com>
Keywords: python,milestone,xprotect,surveillance,camera,security
Classifier: Development Status :: 4 - Beta
Classifier: Intended Audience :: Developers
Classifier: Programming Language :: Python :: 3
Classifier: Operating System :: Microsoft :: Windows
Classifier: Operating System :: MacOS :: MacOS X
Classifier: Operating System :: Unix
Classifier: Topic :: Software Development
Classifier: Topic :: System :: Logging
Classifier: Natural Language :: English
Classifier: License :: Free To Use But Restricted
Requires-Python: >3.4.1
License-File: LICENSE
Requires-Dist: smartinspectPython >=3.0.19
Requires-Dist: requests >=2.0
Requires-Dist: requests-ntlm >=1.2.0
